ao/AO.py
ao/__init__.py
ao/_ao.pypy38-pp73-darwin.so
ao/dataset/__init__.py
ao/dataset/audio.py
ao/dataset/utils.py
ao/evaluate/__init__.py
ao/evaluate/odometry.py
ao/io/__init__.py
ao/io/audio_read.py
ao/io/yaml.py
ao/plot/__init__.py
ao/plot/odometry.py
ao/plot/signal.py
acoustic_odometry-0.0.7.dist-info/LICENSE
acoustic_odometry-0.0.7.dist-info/METADATA
acoustic_odometry-0.0.7.dist-info/WHEEL
acoustic_odometry-0.0.7.dist-info/top_level.txt
acoustic_odometry-0.0.7.dist-info/RECORD
