Metadata-Version: 2.1
Name: acoustic-odometry
Version: 0.0.7
Summary: Acoustic Odometry library
Author-email: Andreu Gimenez <esdandreu@gmail.com>
License: BSD 3-Clause License        
Project-URL: homepage, https://github.com/AcousticOdometry/AO
Project-URL: repository, https://github.com/AcousticOdometry/AO
Keywords: audio,odometry,slam,robotics
Requires-Python: >=3.7
License-File: LICENSE
Requires-Dist: requests
Requires-Dist: numpy
Requires-Dist: matplotlib
Requires-Dist: pyyaml
Requires-Dist: python-dotenv
Requires-Dist: pandas
Requires-Dist: torch
Requires-Dist: torchaudio
Requires-Dist: pytorch-lightning
Requires-Dist: torchmetrics
Requires-Dist: librosa
Provides-Extra: test
Requires-Dist: pytest ; extra == 'test'
